rains/__init__.py
rains/console_rains.py
rains/baseic/__init__.py
rains/baseic/config.py
rains/baseic/decorator.py
rains/baseic/error.py
rains/baseic/log.py
rains/baseic/tools.py
rains/baseic/const/__init__.py
rains/baseic/const/const_api.py
rains/baseic/const/const_state.py
rains/baseic/const/const_sys.py
rains/baseic/const/const_type.py
rains/baseic/environment/__init__.py
rains/baseic/environment/make.py
rains/baseic/interface/__init__.py
rains/baseic/interface/i_driver.py
rains/baseic/interface/i_task.py
rains/baseic/keyword/__init__.py
rains/baseic/keyword/keyword_arg.py
rains/baseic/keyword/keyword_config.py
rains/baseic/keyword/keyword_db.py
rains/baseic/keyword/keyword_task.py
rains/core/__init__.py
rains/core/perform_pool.py
rains/core/perform_server.py
rains/core/common/__init__.py
rains/core/common/action_recorder.py
rains/core/common/driver_agency.py
rains/core/common/pool_runtime.py
rains/core/common/task_diplomatist.py
rains/core/common/task_executor.py
rains/core/common/task_fn_agency.py
rains/core/common/task_instruction.py
rains/external/__init__.py
rains/external/create_project.py
rains/external/create_task.py
rains/external/help.py
rains/external/init_engineering.py
rains/external/order.py
rains/external/run_server.py
rains/external/run_task.py
rains/external/update.py
rains/external/version.py
rains/external/task_template/__init__.py
rains/external/task_template/task_api_template.py
rains/external/task_template/task_web_template.py
rains/kit/__init__.py
rains/kit/api/__init__.py
rains/kit/api/api_driver.py
rains/kit/api/api_plant.py
rains/kit/api/api_task.py
rains/kit/api/packaging/__init__.py
rains/kit/api/packaging/api_plant_handler.py
rains/kit/api/packaging/api_plant_request.py
rains/kit/web/__init__.py
rains/kit/web/web_driver.py
rains/kit/web/web_plant.py
rains/kit/web/web_task.py
rains/kit/web/packaging/__init__.py
rains/kit/web/packaging/web_element_structure.py
rains/kit/web/packaging/web_find_handle.py
rains-0.4.0.dist-info/LICENSE
rains-0.4.0.dist-info/METADATA
rains-0.4.0.dist-info/WHEEL
rains-0.4.0.dist-info/entry_points.txt
rains-0.4.0.dist-info/top_level.txt
rains-0.4.0.dist-info/RECORD
