Metadata-Version: 2.1
Name: rains
Version: 0.4.0
Summary: 这是一个开箱即用、稳定且高效的工程化全栈自动化测试框架。
Home-page: https://gitee.com/catcat7/rains
Author: cat7
Author-email: quinn.7@foxmail.com
License: UNKNOWN
Keywords: rains,test,web,api
Platform: UNKNOWN
Classifier: Programming Language :: Python :: 3
License-File: LICENSE
Requires-Dist: Selenium (==3.14.1)
Requires-Dist: requests
Requires-Dist: flask
